scorecard/__init__.py
scorecard/client.py
scorecard/core/__init__.py
scorecard/core/api_error.py
scorecard/core/client_wrapper.py
scorecard/core/datetime_utils.py
scorecard/core/jsonable_encoder.py
scorecard/core/remove_none_from_dict.py
scorecard/environment.py
scorecard/errors/__init__.py
scorecard/errors/forbidden_error.py
scorecard/errors/not_found_error.py
scorecard/errors/unauthorized_error.py
scorecard/errors/unprocessable_entity_error.py
scorecard/py.typed
scorecard/resources/__init__.py
scorecard/resources/run/__init__.py
scorecard/resources/run/client.py
scorecard/resources/testcase/__init__.py
scorecard/resources/testcase/client.py
scorecard/resources/testrecord/__init__.py
scorecard/resources/testrecord/client.py
scorecard/resources/testset/__init__.py
scorecard/resources/testset/client.py
scorecard/types/__init__.py
scorecard/types/app_create_run_params.py
scorecard/types/app_test_record_create.py
scorecard/types/app_test_set_create.py
scorecard/types/body_text_extract_text_extract_post.py
scorecard/types/create_github_workflow_params.py
scorecard/types/create_run_params.py
scorecard/types/execution_params.py
scorecard/types/http_validation_error.py
scorecard/types/lib_dto_types_create_run_params.py
scorecard/types/lib_dto_types_test_record_create.py
scorecard/types/lib_dto_types_test_set_create.py
scorecard/types/model_params.py
scorecard/types/not_found_error_body.py
scorecard/types/paginated_test_case_response.py
scorecard/types/run_external.py
scorecard/types/run_status.py
scorecard/types/score_execution_params.py
scorecard/types/scoring_params.py
scorecard/types/test_case.py
scorecard/types/test_case_create.py
scorecard/types/test_case_create_input.py
scorecard/types/test_case_custom_inputs.py
scorecard/types/test_case_custom_labels.py
scorecard/types/test_record.py
scorecard/types/test_record_create.py
scorecard/types/test_record_custom_inputs.py
scorecard/types/test_record_custom_labels.py
scorecard/types/test_set_create.py
fern_scorecard-0.1.3.dist-info/METADATA
fern_scorecard-0.1.3.dist-info/WHEEL
fern_scorecard-0.1.3.dist-info/RECORD
